i18ngenerator/__init__.py
i18ngenerator/__main__.py
i18ngenerator/i18ngenerator.py
i18ngenerator/languages.py
i18ngenerator/transformer.py
i18ngenerator/translator.py
i18ngenerator/utils/__init__.py
i18ngenerator/utils/config_parser.py
i18ngenerator/utils/exceptions.py
i18ngenerator/utils/metadata.py
i18ngenerator/utils/utils.py
i18n_generator-1.2.1.dist-info/LICENSE
i18n_generator-1.2.1.dist-info/METADATA
i18n_generator-1.2.1.dist-info/WHEEL
i18n_generator-1.2.1.dist-info/top_level.txt
i18n_generator-1.2.1.dist-info/RECORD
