Metadata-Version: 2.1
Name: i18n-generator
Version: 1.2.1
Summary: Python package for i18n implementation and locales generation
Home-page: https://github.com/LPauzies/i18n-generator
Download-URL: https://pypi.org/project/i18n-generator/
Author: Lucas Pauzies
Author-email: lucas.pauzies@hotmail.fr
Maintainer: Lucas Pauzies
Maintainer-email: lucas.pauzies@hotmail.fr
Project-URL: Documentation, https://github.com/LPauzies/i18n-generator/blob/master/README.md
Project-URL: License, https://github.com/LPauzies/i18n-generator/blob/master/LICENSE
Project-URL: CI, https://github.com/LPauzies/i18n-generator/actions
Project-URL: Bug Tracker, https://github.com/LPauzies/i18n-generator/issues
Project-URL: Source Code, https://github.com/LPauzies/i18n-generator
Project-URL: Funding, https://www.paypal.com/donate/?hosted_button_id=RDDVL7Y5T8MJJ
Classifier: Development Status :: 4 - Beta
Classifier: Natural Language :: English
Classifier: Programming Language :: Python :: 3 :: Only
Classifier: Programming Language :: Python :: 3.8
Classifier: Programming Language :: Python :: 3.9
Classifier: Programming Language :: Python :: 3.10
Classifier: License :: OSI Approved :: GNU General Public License v3 (GPLv3)
Classifier: Operating System :: OS Independent
Classifier: Topic :: Software Development :: Internationalization
Classifier: Topic :: Software Development :: Libraries
Requires-Python: >=3.8
License-File: LICENSE
Requires-Dist: translators (==5.3.1)
Requires-Dist: nltk (>=3.7)
Requires-Dist: pyyaml (==6.0)
